LICENSE
README.rst
setup.py
barnaba/__init__.py
barnaba/_version.py
barnaba/calc_mats.py
barnaba/cluster.py
barnaba/commandline.py
barnaba/definitions.py
barnaba/enm.py
barnaba/escore.py
barnaba/functions.py
barnaba/kde.py
barnaba/model.py
barnaba/nucleic.py
barnaba/reader.py
barnaba/residue.py
barnaba/sec_str_constants.py
barnaba/sec_str_ff.py
barnaba/sec_str_svg.py
barnaba/smm.py
barnaba/smm_old.py
barnaba.egg-info/PKG-INFO
barnaba.egg-info/SOURCES.txt
barnaba.egg-info/dependency_links.txt
barnaba.egg-info/not-zip-safe
barnaba.egg-info/requires.txt
barnaba.egg-info/top_level.txt
bin/barnaba
test/test_angles.py
test/test_annotate.py
test/test_cluster.py
test/test_couplings.py
test/test_dsmotif.py
test/test_dump.py
test/test_enm.py
test/test_ermsd.py
test/test_escore.py
test/test_rmsd.py
test/test_smm.py
test/test_snippet.py
test/test_ssmotif.py
test/test_sugar.py