Metadata-Version: 2.1
Name: barnaba
Version: 0.1.9
Summary: analyze nucleic acid 3D structures and MD trajectories
Home-page: https://github.com/srnas/barnaba
Author: Sandro Bottaro
Author-email: sandro.bottaro@gmail.com
Classifier: Development Status :: 5 - Production/Stable
Classifier: Intended Audience :: Science/Research
Classifier: Topic :: Scientific/Engineering :: Bio-Informatics
Classifier: License :: OSI Approved :: GNU General Public License v3 (GPLv3)
Classifier: Programming Language :: Python :: 3.6
Classifier: Programming Language :: Python :: 3.7
Classifier: Programming Language :: Python :: 3.8
Classifier: Programming Language :: Python :: 3.9
Classifier: Programming Language :: Python :: 3.10
Requires-Python: >=3.6
License-File: LICENSE
